<?xml version="1.0"?>
<opml version="1.0">
  <head>
    <title>newsboat - Exported Feeds</title>
  </head>
  <body>
    <outline type="rss" xmlUrl="https://www.youtube.com/feeds/videos.xml?channel_id=UCjTXJSh3EDxuWQt8b27hTFQ" htmlUrl="https://www.youtube.com/channel/UCjTXJSh3EDxuWQt8b27hTFQ" title="simshadows music"/>
    <outline type="rss" xmlUrl="http://feeds.soundcloud.com/users/soundcloud:users:279933690/sounds.rss" htmlUrl="" title="EmilyOmily (SoundCloud)"/>
    <outline type="rss" xmlUrl="https://www.loudersound.com/feeds/all" htmlUrl="https://www.loudersound.com/feeds/all" title="LouderSound"/>
    <outline type="rss" xmlUrl="http://feeds.feedburner.com/Metalsucks" htmlUrl="http://www.metalsucks.net" title="MetalSucks"/>
    <outline type="rss" xmlUrl="http://feeds.feedburner.com/metalinjection" htmlUrl="http://www.metalinjection.net" title="Metal Injection"/>
    <outline type="rss" xmlUrl="http://www.metalblade.com/us/feed/" htmlUrl="http://www.metalblade.com/us" title="Metal Blade Records"/>
    <outline type="rss" xmlUrl="http://www.folk-metal.nl/feed/" htmlUrl="http://www.folk-metal.nl" title="Folk-metal.nl"/>
    <outline type="rss" xmlUrl="http://www.metalobsession.net/feed/" htmlUrl="http://www.metalobsession.net" title="Metal Obsession"/>
    <outline type="rss" xmlUrl="http://www.metaltalk.net/rss_page.php" htmlUrl="" title=""/>
    <outline type="rss" xmlUrl="http://www.nuclearblast.de/en/label/music/news/feed.xml" htmlUrl="http://www.nuclearblast.de/en/label/music/news/index.html" title="Nuclear Blast - News"/>
    <outline type="rss" xmlUrl="http://www.centurymedia.com/rss/news.ashx" htmlUrl="http://www.centurymedia.com/rss/news.ashx?IdCompany=3" title="Century Media Records News"/>
    <outline type="rss" xmlUrl="http://ocremix.org/feeds/ten20/" htmlUrl="http://www.ocremix.org" title="10 Latest OverClocked ReMixes"/>
    <outline type="rss" xmlUrl="http://blog.noisetrade.com/feed/" htmlUrl="http://blog.noisetrade.com" title="Noisetrade Blog"/>
    <outline type="rss" xmlUrl="http://machinaesupremacyofficial.tumblr.com/rss" htmlUrl="http://machinaesupremacyofficial.tumblr.com/" title="MACHINAE SUPREMACY"/>
    <outline type="rss" xmlUrl="https://www.berliner-philharmoniker.de/en/blog/rss/" htmlUrl="https://www.berliner-philharmoniker.de/en/blog/rss/" title="Berliner Philharmoniker"/>
    <outline type="rss" xmlUrl="http://miracleofsound.net/feed/" htmlUrl="http://miracleofsound.net" title="Miracle of Sound"/>
    <outline type="rss" xmlUrl="https://www.taylordavisviolin.com/feed/" htmlUrl="https://www.taylordavisviolin.com" title="Taylor Davis"/>
  </body>
</opml>
